manual_tls/__init__.py
manual_tls/manual_tls.py
manual_tls-0.0.8.dist-info/METADATA
manual_tls-0.0.8.dist-info/WHEEL
manual_tls-0.0.8.dist-info/licenses/LICENSE
manual_tls-0.0.8.dist-info/RECORD
