Metadata-Version: 2.3
Name: manual_tls
Version: 0.0.8
Summary: A tiny TLS 1.3 pure Python implementation
Project-URL: Homepage, https://github.com/watsug/manual-tls
Project-URL: Issues, https://github.com/watsug/manual-tls
Author-email: Alexander Bersenev / Adam Augustyn <watsug@gmail.com>
License-File: LICENSE
Classifier: License :: OSI Approved :: MIT License
Classifier: Operating System :: OS Independent
Classifier: Programming Language :: Python :: 3
Requires-Python: >=3.8
Requires-Dist: ecdsa
